{
  "data_pattern": {
    "name": "usoskin_high_performance",
    "description": "\u9488\u5bf9Usoskin\u6570\u636e\u7684\u9ad8\u6027\u80fd\u7b56\u7565",
    "pattern": {
      "n_features_range": [
        15000,
        20000
      ],
      "n_samples_range": [
        600,
        700
      ],
      "n_classes": 4,
      "data_type": "scRNA_neurons"
    }
  },
  "optimal_strategy": {
    "algorithm": "boundary_failure_learning",
    "pca_components": 20,
    "random_state": 42,
    "gmm_config": {
      "covariance_type": "full",
      "n_init": 10,
      "reg_covar": 1e-06
    },
    "expected_nmi": 0.9097,
    "confidence": 0.95
  },
  "alternative_strategies": [
    {
      "algorithm": "boundary_failure_learning",
      "pca_components": 30,
      "expected_nmi": 0.85
    },
    {
      "algorithm": "ultimate_fusion_framework",
      "pca_components": 50,
      "expected_nmi": 0.75
    }
  ]
}